{
  "name": "donutchart",
  "type": "registry:ui",
  "title": "DonutChart",
  "description": "Donut with center figure + legend; hover highlights a slice. Colors default to the brand ramp.",
  "files": [
    {
      "path": "apps/www/registry/ui/data/DonutChart.jsx",
      "type": "registry:ui",
      "content": "import React from 'react';\nimport { injectEfCss } from '../forms/Button.jsx';\nconst CSS = `\n.ef-donut{display:flex;align-items:center;gap:20px}\n.ef-donut__legend{display:flex;flex-direction:column;gap:8px}\n.ef-donut__item{display:flex;align-items:center;gap:8px;font-size:var(--text-sm);color:var(--text-secondary);border:none;background:none;padding:0;cursor:default;font-family:var(--font-sans);text-align:left}\n.ef-donut__swatch{width:9px;height:9px;border-radius:2px;flex:none}\n.ef-donut__val{margin-left:auto;font-family:var(--font-mono);font-size:12px;color:var(--text-primary);padding-left:14px}\n`;\nconst PALETTE = ['var(--brand-950)', 'var(--brand-500)', 'var(--brand-200)', 'var(--sand-400)', 'var(--sand-200)'];\nexport function DonutChart({ data, size = 140, thickness = 16, centerLabel, centerValue, format, style, className }) {\n  injectEfCss('ef-css-donut', CSS);\n  const [hov, setHov] = React.useState(null);\n  const total = data.reduce((s, d) => s + d.value, 0) || 1;\n  const R = 50 - thickness / 100 * 50;\n  const C = 2 * Math.PI * R;\n  let acc = 0;\n  const segs = data.map((d, i) => {\n    const frac = d.value / total;\n    const seg = { ...d, i, dash: `${Math.max(frac * C - 1.5, 0.5)} ${C}`, offset: -acc * C, color: d.color || PALETTE[i % PALETTE.length] };\n    acc += frac;\n    return seg;\n  });\n  return (\n    <div className={`ef-donut${className ? ' ' + className : ''}`} style={style}>\n      <div style={{ position: 'relative', width: size, height: size, flex: 'none' }}>\n        <svg viewBox=\"0 0 100 100\" width={size} height={size} style={{ transform: 'rotate(-90deg)' }}>\n          {segs.map(s => (\n            <circle key={s.i} cx=\"50\" cy=\"50\" r={R} fill=\"none\" stroke={s.color} strokeWidth={thickness * (hov === s.i ? 1.15 : 1)}\n              strokeDasharray={s.dash} strokeDashoffset={s.offset} style={{ transition: 'stroke-width 120ms var(--ease-out)' }}\n              onMouseEnter={() => setHov(s.i)} onMouseLeave={() => setHov(null)} />\n          ))}\n        </svg>\n        <div style={{ position: 'absolute', inset: 0, display: 'flex', flexDirection: 'column', alignItems: 'center', justifyContent: 'center', pointerEvents: 'none' }}>\n          <span style={{ fontFamily: 'var(--font-mono)', fontSize: Math.round(size * 0.16), fontWeight: 600, color: 'var(--text-primary)' }}>\n            {hov != null ? (format ? format(segs[hov].value) : segs[hov].value.toLocaleString()) : centerValue}\n          </span>\n          <span style={{ fontSize: 11, color: 'var(--text-muted)' }}>{hov != null ? segs[hov].label : centerLabel}</span>\n        </div>\n      </div>\n      <div className=\"ef-donut__legend\">\n        {segs.map(s => (\n          <span key={s.i} className=\"ef-donut__item\" onMouseEnter={() => setHov(s.i)} onMouseLeave={() => setHov(null)} style={{ opacity: hov == null || hov === s.i ? 1 : .45, transition: 'opacity 120ms var(--ease-out)' }}>\n            <span className=\"ef-donut__swatch\" style={{ background: s.color }}></span>\n            {s.label}\n            <span className=\"ef-donut__val\">{Math.round(s.value / total * 100)}%</span>\n          </span>\n        ))}\n      </div>\n    </div>\n  );\n}\n"
    },
    {
      "path": "apps/www/registry/ui/data/DonutChart.d.ts",
      "type": "registry:component",
      "content": "export interface DonutSlice { label: string; value: number; /** Defaults to brand palette */ color?: string; }\nexport interface DonutChartProps {\n  data: DonutSlice[];\n  /** Px @default 140 */\n  size?: number;\n  /** Ring thickness (viewBox units) @default 16 */\n  thickness?: number;\n  /** Center caption */\n  centerLabel?: React.ReactNode;\n  /** Center figure */\n  centerValue?: React.ReactNode;\n  /** Hover value formatter */\n  format?: (value: number) => string;\n  style?: React.CSSProperties;\n  className?: string;\n}\nexport declare function DonutChart(props: DonutChartProps): JSX.Element;\n"
    },
    {
      "path": "apps/www/registry/ui/data/DonutChart.prompt.md",
      "type": "registry:component",
      "content": "Donut with center figure + legend; hover highlights a slice. Colors default to the brand ramp.\n\n```jsx\n<DonutChart centerValue=\"$8.4k\" centerLabel=\"This month\" data={[\n  { label: 'Agent', value: 4200 }, { label: 'Infra', value: 2600 }, { label: 'Node', value: 1600 },\n]} />\n```\n"
    }
  ],
  "categories": [
    "data"
  ],
  "$schema": "https://ui.shadcn.com/schema/registry-item.json"
}
